postage/messaging.py
postage/microthreads.py
postage/__init__.py
postage-1.0.0.dist-info/pydist.json
postage-1.0.0.dist-info/METADATA
postage-1.0.0.dist-info/RECORD
postage-1.0.0.dist-info/DESCRIPTION.rst
postage-1.0.0.dist-info/WHEEL
postage-1.0.0.dist-info/top_level.txt
